docpack/__init__.py
docpack/_version.py
docpack/api.py
docpack/confluence_fetcher.py
docpack/constants.py
docpack/find_matching_files.py
docpack/github_fetcher.py
docpack/paths.py
docpack/vendor/__init__.py
docpack/vendor/pytest_cov_helper.py
docpack-0.1.6.dist-info/AUTHORS.rst
docpack-0.1.6.dist-info/LICENSE.txt
docpack-0.1.6.dist-info/METADATA
docpack-0.1.6.dist-info/WHEEL
docpack-0.1.6.dist-info/RECORD
